{"trial_id": "02", "hyperparameters": {"space": [{"class_name": "Int", "config": {"name": "lstm1_units", "default": null, "conditions": [], "min_value": 24, "max_value": 64, "step": 8, "sampling": "linear"}}, {"class_name": "Int", "config": {"name": "lstm2_units", "default": null, "conditions": [], "min_value": 24, "max_value": 64, "step": 8, "sampling": "linear"}}, {"class_name": "Boolean", "config": {"name": "dense_layer", "default": false, "conditions": []}}, {"class_name": "Int", "config": {"name": "dense_units", "default": null, "conditions": [], "min_value": 24, "max_value": 32, "step": 8, "sampling": "linear"}}], "values": {"lstm1_units": 48, "lstm2_units": 56, "dense_layer": false, "dense_units": 24}}, "metrics": {"metrics": {"loss": {"direction": "min", "observations": [{"value": [0.12380360811948776], "step": 12}]}, "mean_absolute_error": {"direction": "min", "observations": [{"value": [0.1902780383825302], "step": 12}]}, "val_loss": {"direction": "min", "observations": [{"value": [0.1298317164182663], "step": 12}]}, "val_mean_absolute_error": {"direction": "min", "observations": [{"value": [0.17199474573135376], "step": 12}]}}}, "score": 0.1298317164182663, "best_step": 12, "status": "COMPLETED", "message": null}